yamlgator/YAMLator.py
yamlgator/__init__.py
yamlgator/constants.py
yamlgator/evaluators/AbstractEvaluator.py
yamlgator/evaluators/AbstractObservable.py
yamlgator/evaluators/AbstractState.py
yamlgator/evaluators/Observables.py
yamlgator/evaluators/StateEvaluator.py
yamlgator/evaluators/States.py
yamlgator/evaluators/__init__.py
yamlgator/objdb.py
yamlgator/transformers/AtTransformer.py
yamlgator/transformers/BangTransformer.py
yamlgator/transformers/IfTransformer.py
yamlgator/transformers/ImportTransformer.py
yamlgator/transformers/KeyChainTransformer.py
yamlgator/transformers/KeyTransformer.py
yamlgator/transformers/ObjectTransformer.py
yamlgator/transformers/PathValueTransformer.py
yamlgator/transformers/PlainTextTransformer.py
yamlgator/transformers/PythonTransformer.py
yamlgator/transformers/Transformer.py
yamlgator/transformers/ValueTransformer.py
yamlgator/transformers/YAMLTransformer.py
yamlgator/transformers/__init__.py
yamlgator/tree.py
yamlgator/utree.py
yamlgator/validators/AbstractValidator.py
yamlgator/validators/ValueValidator.py
yamlgator/validators/__init__.py
yamlgator/validators/issues.py
yamlgator-0.2.6.dist-info/METADATA
yamlgator-0.2.6.dist-info/WHEEL
yamlgator-0.2.6.dist-info/licenses/LICENSE
yamlgator-0.2.6.dist-info/RECORD
