Metadata-Version: 2.4
Name: yamlgator
Version: 0.2.6
Summary: A macro language for yaml documents.
License-File: LICENSE
Author: jeff
Author-email: jeff@thinkae.org
Requires-Python: >=3.9,<4.0
Classifier: Programming Language :: Python :: 3
Classifier: Programming Language :: Python :: 3.9
Classifier: Programming Language :: Python :: 3.10
Classifier: Programming Language :: Python :: 3.11
Classifier: Programming Language :: Python :: 3.12
Classifier: Programming Language :: Python :: 3.13
Classifier: Programming Language :: Python :: 3.14
Requires-Dist: astor
Requires-Dist: pyyaml
Requires-Dist: yarl
